AndrezaSantosCalc/__init__.py
AndrezaSantosCalc/calculadora.py
AndrezaSantosCalc-1.0.3.dist-info/METADATA
AndrezaSantosCalc-1.0.3.dist-info/WHEEL
AndrezaSantosCalc-1.0.3.dist-info/top_level.txt
AndrezaSantosCalc-1.0.3.dist-info/RECORD
