Metadata-Version: 2.1
Name: AndrezaSantosCalc
Version: 1.0.3
Summary: Uma biblioteca para realizar operações básicas de uma calculadora.
Author: Andreza Santos
Author-email: seu_email@example.com
License: MIT
Classifier: Programming Language :: Python :: 3
Classifier: Programming Language :: Python :: 3.7
Classifier: Programming Language :: Python :: 3.8
Classifier: Programming Language :: Python :: 3.9
Classifier: Programming Language :: Python :: 3.10
Classifier: License :: OSI Approved :: MIT License
Classifier: Operating System :: OS Independent
